odoo/addons/partner_restrict_payment_acquirer/README.rst
odoo/addons/partner_restrict_payment_acquirer/__init__.py
odoo/addons/partner_restrict_payment_acquirer/__manifest__.py
odoo/addons/partner_restrict_payment_acquirer/i18n/es.po
odoo/addons/partner_restrict_payment_acquirer/i18n/it.po
odoo/addons/partner_restrict_payment_acquirer/i18n/partner_restrict_payment_acquirer.pot
odoo/addons/partner_restrict_payment_acquirer/models/__init__.py
odoo/addons/partner_restrict_payment_acquirer/models/payment_provider.py
odoo/addons/partner_restrict_payment_acquirer/models/res_partner.py
odoo/addons/partner_restrict_payment_acquirer/readme/DESCRIPTION.md
odoo/addons/partner_restrict_payment_acquirer/readme/ROADMAP.md
odoo/addons/partner_restrict_payment_acquirer/readme/USAGE.md
odoo/addons/partner_restrict_payment_acquirer/static/description/icon.png
odoo/addons/partner_restrict_payment_acquirer/static/description/index.html
odoo/addons/partner_restrict_payment_acquirer/tests/__init__.py
odoo/addons/partner_restrict_payment_acquirer/tests/test_payment_provider.py
odoo/addons/partner_restrict_payment_acquirer/views/res_partner_views.xml
odoo_addon_partner_restrict_payment_acquirer-17.0.1.0.0.4.dist-info/METADATA
odoo_addon_partner_restrict_payment_acquirer-17.0.1.0.0.4.dist-info/WHEEL
odoo_addon_partner_restrict_payment_acquirer-17.0.1.0.0.4.dist-info/top_level.txt
odoo_addon_partner_restrict_payment_acquirer-17.0.1.0.0.4.dist-info/RECORD
